{
  "mejora": {
    "id": "MEJORA-0eb9f46be230d815",
    "timestamp": "2026-02-04T00:04:27.646849+00:00",
    "descripcion": "Optimizaci\u00f3n autom\u00e1tica ciclo 1",
    "codigo_seguro": "\n# C\u00d3DIGO GENERADO AUTOM\u00c1TICAMENTE - CICLO 1\ndef optimizar_ia_0eb9f46be230d815():\n    return {\"status\": \"OPTIMIZADO\", \"timestamp\": \"2026-02-04T00:04:27.646889+00:00\"}\n",
    "evidencia": {
      "timestamp_unix": 1770163467,
      "hash_verificacion": "252693a81299",
      "memoria_usada": "REAL",
      "procesamiento": "ACTIVO"
    },
    "estado": "APLICADA_AUTOMATICAMENTE"
  },
  "verificacion": "100% REAL Y TANGIBLE",
  "timestamp_validacion": "2026-02-04T00:04:27.647681+00:00"
}